{
  "project_info": {
    "project_number": "694363547866",
    "project_id": "softec-app-dev-1c0e3",
    "storage_bucket": "softec-app-dev-1c0e3.appspot.com"
  },
  "client": [
    {
      "client_info": {
        "mobilesdk_app_id": "1:694363547866:android:269cf89a4f0030e2c81de3",
        "android_client_info": {
          "package_name": "com.example.softec_app_dev"
        }
      },
      "oauth_client": [],
      "api_key": [
        {
          "current_key": "AIzaSyAHHCYO1-QEnm9te04ds_B_N88pIQSi89Y"
        }
      ],
      "services": {
        "appinvite_service": {
          "other_platform_oauth_client": []
        }
      }
    }
  ],
  "configuration_version": "1"
}